logger_uuid/__init__.py
logger_uuid/logger.py
logger_uuid-1.0.0.dist-info/LICENSE
logger_uuid-1.0.0.dist-info/METADATA
logger_uuid-1.0.0.dist-info/WHEEL
logger_uuid-1.0.0.dist-info/top_level.txt
logger_uuid-1.0.0.dist-info/RECORD
