Metadata-Version: 2.1
Name: logger-uuid
Version: 1.0.0
Summary: Implement logs with unique uuid identifier.
Home-page: https://github.com/anddyagudelo/logger-uuid
Author: Anddy Agudelo
Author-email: andiagudelo@gmail.com
License: MIT
License-File: LICENSE
